pyburn-0.1.7.dist-info/METADATA
pyburn-0.1.7.dist-info/WHEEL
pyburn/__init__.py
pyburn/pyburn.cpython-314-i386-linux-gnu.so
pyburn-0.1.7.dist-info/RECORD
