Metadata-Version: 2.4
Name: pyburn
Version: 0.1.7
Classifier: Programming Language :: Rust
Classifier: Programming Language :: Python :: Implementation :: CPython
Classifier: Programming Language :: Python :: Implementation :: PyPy
Requires-Dist: wgpu ; extra == 'wgpu'
Requires-Dist: ndarray ; extra == 'ndarray'
Provides-Extra: wgpu
Provides-Extra: ndarray
Requires-Python: >=3.8
Project-URL: Homepage, https://github.com/kwachojunga/wrapburn.git
